{"is_source_file": true, "format": "TypeScript/TSX", "description": "This file is the entry point for a React application, responsible for rendering the main App component into the DOM.", "external_files": ["./App", "./styles.css"], "external_methods": ["ReactDOM.createRoot"], "published": [], "classes": [], "methods": ["ReactDOM.createRoot"], "calls": ["ReactDOM.createRoot", "document.getElementById"], "search-terms": ["React", "TypeScript", "frontend", "main.tsx", "render", "entry point"], "state": 2, "file_id": 11, "knowledge_revision": 28, "git_revision": "6ee47d13eee6483fd2ba249e360f654e8bc677a5", "ctags": [], "hash": "fc1cfacc070f64e7380401cae205e22d", "format-version": 4, "code-base-name": "fastapi_backend", "filename": "frontend/src/main.tsx", "revision_history": [{"28": "6ee47d13eee6483fd2ba249e360f654e8bc677a5"}]}